gcsannex.py
gcsannex-0.2.dist-info/top_level.txt
gcsannex-0.2.dist-info/metadata.json
gcsannex-0.2.dist-info/DESCRIPTION.rst
gcsannex-0.2.dist-info/entry_points.txt
gcsannex-0.2.dist-info/WHEEL
gcsannex-0.2.dist-info/METADATA
gcsannex-0.2.dist-info/RECORD
