Metadata-Version: 2.0
Name: gcsannex
Version: 0.2
Summary: git-annex external special remote for Google Cloud Storage
Home-page: https://github.com/bgilbert/gcsannex
Author: Benjamin Gilbert
Author-email: bgilbert@backtick.net
License: GPLv3+
Keywords: git-annex gcs Google Cloud Storage
Platform: UNKNOWN
Classifier: Development Status :: 4 - Beta
Classifier: Environment :: Plugins
Classifier: Intended Audience :: End Users/Desktop
Classifier: License :: OSI Approved :: GNU General Public License v3 or later (GPLv3+)
Classifier: Operating System :: OS Independent
Classifier: Programming Language :: Python :: 2
Classifier: Programming Language :: Python :: 2.7
Classifier: Topic :: System :: Archiving
Requires-Dist: google-api-python-client
Requires-Dist: PyCrypto
